odoo/addons/stock_quant_safe_inventory/README.rst
odoo/addons/stock_quant_safe_inventory/__init__.py
odoo/addons/stock_quant_safe_inventory/__manifest__.py
odoo/addons/stock_quant_safe_inventory/i18n/fr.po
odoo/addons/stock_quant_safe_inventory/i18n/fr_FR.po
odoo/addons/stock_quant_safe_inventory/i18n/it.po
odoo/addons/stock_quant_safe_inventory/i18n/stock_quant_safe_inventory.pot
odoo/addons/stock_quant_safe_inventory/models/__init__.py
odoo/addons/stock_quant_safe_inventory/models/res_company.py
odoo/addons/stock_quant_safe_inventory/models/res_config_settings.py
odoo/addons/stock_quant_safe_inventory/models/stock_quant.py
odoo/addons/stock_quant_safe_inventory/readme/CONTEXT.md
odoo/addons/stock_quant_safe_inventory/readme/CONTRIBUTORS.md
odoo/addons/stock_quant_safe_inventory/readme/DESCRIPTION.md
odoo/addons/stock_quant_safe_inventory/readme/USAGE.md
odoo/addons/stock_quant_safe_inventory/static/description/icon.png
odoo/addons/stock_quant_safe_inventory/static/description/index.html
odoo/addons/stock_quant_safe_inventory/tests/__init__.py
odoo/addons/stock_quant_safe_inventory/tests/test_safe_inventory.py
odoo/addons/stock_quant_safe_inventory/views/res_config_settings.xml
odoo_addon_stock_quant_safe_inventory-16.0.1.0.1.dist-info/METADATA
odoo_addon_stock_quant_safe_inventory-16.0.1.0.1.dist-info/WHEEL
odoo_addon_stock_quant_safe_inventory-16.0.1.0.1.dist-info/top_level.txt
odoo_addon_stock_quant_safe_inventory-16.0.1.0.1.dist-info/RECORD
